[
    {
        "company": "Lorem augu", 
        "create_time": 147941332213, 
        "emoji": "e1f627", 
        "id": "id4ddafddc-d275-44fd-ad4c-00b559f2823e", 
        "position": "Purus lacu", 
        "review": "Class morb"
    }, 
    {
        "company": "Fames risu", 
        "create_time": 147941346831, 
        "emoji": "e1f631", 
        "id": "id372e52f2-fae6-46df-b933-6d80e3b32768", 
        "position": "Ipsum mass", 
        "review": "Justo clas"
    }, 
    {
        "company": "Ipsum lacu", 
        "create_time": 147941352455, 
        "emoji": "e1f620", 
        "id": "id6db93bf3-0791-4259-9660-dbdee31c854d", 
        "position": "Netus morb", 
        "review": "Nulla morb"
    }, 
    {
        "company": "Curae done", 
        "create_time": 147941331195, 
        "emoji": "e1f631", 
        "id": "id711f9990-4b17-4d6f-9c78-7a6e08ea3722", 
        "position": "Fames dolo", 
        "review": "Velit ipsu"
    }, 
    {
        "company": "Netus lore", 
        "create_time": 147941350149, 
        "emoji": "e1f634", 
        "id": "id49219864-b8f6-4f45-a5d8-9bbca3e0dcda", 
        "position": "Porta netu", 
        "review": "Morbi proi"
    }
]